harmony_model_checker/__init__.py
harmony_model_checker/charm.cp37-win_amd64.pyd
harmony_model_checker/compile.py
harmony_model_checker/config.py
harmony_model_checker/dfacmp.py
harmony_model_checker/exception.py
harmony_model_checker/iface.py
harmony_model_checker/main.py
harmony_model_checker/charm/charm.c
harmony_model_checker/charm/charm.h
harmony_model_checker/charm/code.c
harmony_model_checker/charm/code.h
harmony_model_checker/charm/dfa.c
harmony_model_checker/charm/dfa.h
harmony_model_checker/charm/dot.c
harmony_model_checker/charm/dot.h
harmony_model_checker/charm/global.c
harmony_model_checker/charm/global.h
harmony_model_checker/charm/graph.c
harmony_model_checker/charm/graph.h
harmony_model_checker/charm/hashdict.c
harmony_model_checker/charm/hashdict.h
harmony_model_checker/charm/hashset.c
harmony_model_checker/charm/hashset.h
harmony_model_checker/charm/head.h
harmony_model_checker/charm/json.c
harmony_model_checker/charm/json.h
harmony_model_checker/charm/minheap.c
harmony_model_checker/charm/minheap.h
harmony_model_checker/charm/ops.c
harmony_model_checker/charm/ops.h
harmony_model_checker/charm/queue.c
harmony_model_checker/charm/queue.h
harmony_model_checker/charm/spawn.h
harmony_model_checker/charm/stack.c
harmony_model_checker/charm/stack.h
harmony_model_checker/charm/strbuf.c
harmony_model_checker/charm/strbuf.h
harmony_model_checker/charm/thread.c
harmony_model_checker/charm/thread.h
harmony_model_checker/charm/value.c
harmony_model_checker/charm/value.h
harmony_model_checker/charm/iface/iface.c
harmony_model_checker/charm/iface/iface.h
harmony_model_checker/charm/iface/iface_graph.c
harmony_model_checker/charm/iface/iface_graph.h
harmony_model_checker/charm/ipi/ipi.c
harmony_model_checker/charm/python_ext/ext.c
harmony_model_checker/harmony/AbstractASTVisitor.py
harmony_model_checker/harmony/DumpASTVisitor.py
harmony_model_checker/harmony/__init__.py
harmony_model_checker/harmony/ast.py
harmony_model_checker/harmony/bag_util.py
harmony_model_checker-1.2.2769.dist-info/LICENSE
harmony_model_checker-1.2.2769.dist-info/METADATA
harmony_model_checker-1.2.2769.dist-info/WHEEL
harmony_model_checker-1.2.2769.dist-info/entry_points.txt
harmony_model_checker-1.2.2769.dist-info/top_level.txt
harmony_model_checker-1.2.2769.dist-info/RECORD
