Metadata-Version: 2.1
Name: harmony_model_checker
Version: 1.2.2769
Summary: Harmony Programming Language
Home-page: https://harmony.cs.cornell.edu
Author: Robbert van Renesse
Author-email: rvr@cs.cornell.edu
License: BSD
Platform: UNKNOWN
Requires-Python: >=3.6
